{
	"info": {
		"_postman_id": "87e41ab4-e356-4ee5-af18-432e9f0714b9",
		"name": "CRUD-final",
		"schema": "https://schema.getpostman.com/json/collection/v2.1.0/collection.json"
	},
	"item": [
		{
			"name": "Estudiantes",
			"item": [
				{
					"name": "Guardar estudiante",
					"request": {
						"method": "POST",
						"header": [],
						"body": {
							"mode": "raw",
							"raw": "{\r\n    \"id\":\"002\",\r\n    \"nombre\":\"Hunter Douglas\",\r\n    \"aprobado\":true\r\n}",
							"options": {
								"raw": {
									"language": "json"
								}
							}
						},
						"url": {
							"raw": "localhost:3312/api/v1/nuevoEstudiante",
							"host": [
								"localhost"
							],
							"port": "3312",
							"path": [
								"api",
								"v1",
								"nuevoEstudiante"
							]
						}
					},
					"response": []
				},
				{
					"name": "Obten todos",
					"request": {
						"method": "GET",
						"header": [],
						"url": {
							"raw": "localhost:3312/api/v1/estudiantes",
							"host": [
								"localhost"
							],
							"port": "3312",
							"path": [
								"api",
								"v1",
								"estudiantes"
							]
						}
					},
					"response": []
				},
				{
					"name": "Obten estudiante id",
					"request": {
						"method": "GET",
						"header": [],
						"url": {
							"raw": "localhost:3312/api/v1/estudiantes002",
							"host": [
								"localhost"
							],
							"port": "3312",
							"path": [
								"api",
								"v1",
								"estudiantes002"
							]
						}
					},
					"response": []
				},
				{
					"name": "Borrar estudiante",
					"request": {
						"method": "DELETE",
						"header": [],
						"url": {
							"raw": "localhost:3312/api/v1/eliminarEstudiante002",
							"host": [
								"localhost"
							],
							"port": "3312",
							"path": [
								"api",
								"v1",
								"eliminarEstudiante002"
							]
						}
					},
					"response": []
				},
				{
					"name": "Actualizar estudiante",
					"request": {
						"method": "PUT",
						"header": [],
						"body": {
							"mode": "raw",
							"raw": "{\r\n    \"_id\": \"637aa59cb257d1707d9aa5a7\",\r\n    \"id\":\"001\",\r\n    \"nombre\": \"Jose Casal\",\r\n    \"aprobado\": true\r\n}",
							"options": {
								"raw": {
									"language": "json"
								}
							}
						},
						"url": {
							"raw": "localhost:3312/api/v1/actualizarEstudiante",
							"host": [
								"localhost"
							],
							"port": "3312",
							"path": [
								"api",
								"v1",
								"actualizarEstudiante"
							]
						}
					},
					"response": []
				}
			]
		}
	]
}